echoes/__init__.py
echoes/datasets.py
echoes/utils.py
echoes/data/mackey_glass_t17.npy
echoes/esn/__init__.py
echoes/esn/_base.py
echoes/esn/_generator.py
echoes/esn/_regressor.py
echoes/plotting/__init__.py
echoes/plotting/_core.py
echoes/plotting/_memory_capacity.py
echoes/reservoir/__init__.py
echoes/reservoir/_leaky_numba.py
echoes-1.0.2.dist-info/licenses/LICENSE
echoes-1.0.2.dist-info/METADATA
echoes-1.0.2.dist-info/WHEEL
echoes-1.0.2.dist-info/top_level.txt
echoes-1.0.2.dist-info/RECORD
