Metadata-Version: 2.4
Name: echoes
Version: 1.0.2
Summary: Machine Learning with Echo State Networks in Python
Author-email: Fabrizio Damicelli <fabridamicelli@gmail.com>
License-Expression: MIT
Project-URL: Changelog, https://github.com/fabridamicelli/echoes/blob/main/CHANGELOG.md
Project-URL: Repository, https://github.com/fabridamicelli/echoes
Project-URL: Documentation, https://fabridamicelli.github.io/echoes
Keywords: python,machine-learning,shallow-learning,neural-networks,recurrent-neural-networks,reservoir-computing,echo-state-network
Classifier: Operating System :: OS Independent
Classifier: Programming Language :: Python :: 3 :: Only
Classifier: Programming Language :: Python :: 3.9
Classifier: Programming Language :: Python :: 3.10
Classifier: Programming Language :: Python :: 3.11
Classifier: Programming Language :: Python :: 3.12
Classifier: Programming Language :: Python :: 3.13
Classifier: Intended Audience :: Science/Research
Classifier: Intended Audience :: Developers
Classifier: Topic :: Scientific/Engineering
Classifier: Topic :: Scientific/Engineering :: Artificial Intelligence
Requires-Python: >=3.9
License-File: LICENSE
Requires-Dist: numpy>=1.23.5
Requires-Dist: scikit-learn>=1.2.0
Requires-Dist: pandas>=1.0.3
Requires-Dist: matplotlib>=3.2.0
Requires-Dist: seaborn>=0.10.1
Requires-Dist: numba>=0.56.4
Dynamic: license-file
